{
  "ID": "5e8b0567-226a-4508-92b5-74621e652c5f",
  "Version": "2.3.4",
  "Name": "shopLayer",
  "Content": {
    "Content": {
      "Animation": {
        "Duration": 0,
        "Speed": 1.0,
        "Timelines": [],
        "ctype": "TimelineActionData"
      },
      "AnimationList": [],
      "ObjectData": {
        "Tag": 6,
        "Children": [
          {
            "FileData": {
              "Type": "Normal",
              "Path": "mainBg.png",
              "Plist": ""
            },
            "Scale9OriginX": 247,
            "Scale9OriginY": 440,
            "Scale9Width": 256,
            "Scale9Height": 454,
            "TouchEnable": true,
            "AnchorPoint": {
              "ScaleX": 0.5,
              "ScaleY": 0.5
            },
            "Position": {
              "X": 375.0,
              "Y": 667.0
            },
            "Scale": {
              "ScaleX": 1.0,
              "ScaleY": 1.0
            },
            "CColor": {},
            "IconVisible": false,
            "PositionPercentXEnabled": true,
            "PositionPercentYEnabled": true,
            "PrePosition": {
              "X": 0.5,
              "Y": 0.5
            },
            "PreSize": {
              "X": 1.0,
              "Y": 1.0
            },
            "Tag": 7,
            "ActionTag": -868469218,
            "Size": {
              "X": 750.0,
              "Y": 1334.0
            },
            "Name": "bg",
            "ctype": "ImageViewObjectData"
          },
          {
            "FontSize": 100,
            "LabelText": "商店",
            "OutlineColor": {
              "G": 0,
              "B": 0
            },
            "ShadowColor": {
              "R": 110,
              "G": 110,
              "B": 110
            },
            "ShadowOffsetX": 2.0,
            "ShadowOffsetY": -2.0,
            "AnchorPoint": {
              "ScaleX": 0.5,
              "ScaleY": 0.5
            },
            "Position": {
              "X": 375.0,
              "Y": 1182.17
            },
            "Scale": {
              "ScaleX": 1.0,
              "ScaleY": 1.0
            },
            "CColor": {
              "R": 106,
              "G": 0,
              "B": 95
            },
            "IconVisible": false,
            "PositionPercentXEnabled": true,
            "PrePosition": {
              "X": 0.5,
              "Y": 0.8862
            },
            "PreSize": {
              "X": 0.2667,
              "Y": 0.075
            },
            "LeftMargin": 275.0,
            "RightMargin": 275.0,
            "TopMargin": 101.83,
            "BottomMargin": 1132.17,
            "Tag": 11,
            "ActionTag": 461425916,
            "Size": {
              "X": 200.0,
              "Y": 100.0
            },
            "Name": "title",
            "ctype": "TextObjectData"
          },
          {
            "FontSize": 14,
            "ButtonText": "",
            "TextColor": {
              "R": 65,
              "G": 65,
              "B": 70
            },
            "NormalFileData": {
              "Type": "Normal",
              "Path": "setting/guanbi.png",
              "Plist": ""
            },
            "Scale9Enable": true,
            "Scale9OriginX": 15,
            "Scale9OriginY": 11,
            "Scale9Width": 82,
            "Scale9Height": 146,
            "OutlineColor": {
              "G": 0,
              "B": 0
            },
            "ShadowColor": {
              "R": 110,
              "G": 110,
              "B": 110
            },
            "ShadowOffsetX": 2.0,
            "ShadowOffsetY": -2.0,
            "TouchEnable": true,
            "AnchorPoint": {
              "ScaleX": 0.5,
              "ScaleY": 0.5
            },
            "Position": {
              "X": 375.0,
              "Y": 255.9706
            },
            "Scale": {
              "ScaleX": 1.0,
              "ScaleY": 1.0
            },
            "CColor": {},
            "IconVisible": false,
            "PositionPercentXEnabled": true,
            "PrePosition": {
              "X": 0.5,
              "Y": 0.1919
            },
            "PreSize": {
              "X": 0.1493,
              "Y": 0.1259
            },
            "LeftMargin": 319.0,
            "RightMargin": 319.0,
            "TopMargin": 994.0294,
            "BottomMargin": 171.9706,
            "Tag": 5,
            "ActionTag": 1651388501,
            "Size": {
              "X": 112.0,
              "Y": 168.0
            },
            "Name": "btn_close",
            "ctype": "ButtonObjectData"
          },
          {
            "FontSize": 14,
            "ButtonText": "",
            "TextColor": {
              "R": 65,
              "G": 65,
              "B": 70
            },
            "DisabledFileData": {
              "Type": "Normal",
              "Path": "shop/itemBg.png",
              "Plist": ""
            },
            "PressedFileData": {
              "Type": "Normal",
              "Path": "shop/itemBg.png",
              "Plist": ""
            },
            "NormalFileData": {
              "Type": "Normal",
              "Path": "shop/itemBg.png",
              "Plist": ""
            },
            "Scale9Enable": true,
            "Scale9OriginX": 15,
            "Scale9OriginY": 11,
            "Scale9Width": 146,
            "Scale9Height": 201,
            "OutlineColor": {
              "G": 0,
              "B": 0
            },
            "ShadowColor": {
              "R": 110,
              "G": 110,
              "B": 110
            },
            "ShadowOffsetX": 2.0,
            "ShadowOffsetY": -2.0,
            "TouchEnable": true,
            "AnchorPoint": {
              "ScaleX": 0.5,
              "ScaleY": 0.5
            },
            "Position": {
              "X": 206.2203,
              "Y": 942.4209
            },
            "Scale": {
              "ScaleX": 1.0,
              "ScaleY": 1.0
            },
            "CColor": {},
            "IconVisible": false,
            "PrePosition": {
              "X": 0.275,
              "Y": 0.7065
            },
            "PreSize": {
              "X": 0.2347,
              "Y": 0.1672
            },
            "LeftMargin": 118.2203,
            "RightMargin": 455.7797,
            "TopMargin": 280.0791,
            "BottomMargin": 830.9209,
            "Tag": 98,
            "Children": [
              {
                "FontSize": 36,
                "LabelText": "X10",
                "OutlineColor": {
                  "G": 0,
                  "B": 0
                },
                "ShadowColor": {
                  "R": 110,
                  "G": 110,
                  "B": 110
                },
                "ShadowOffsetX": 2.0,
                "ShadowOffsetY": -2.0,
                "AnchorPoint": {
                  "ScaleX": 0.5,
                  "ScaleY": 0.5
                },
                "Position": {
                  "X": 88.0,
                  "Y": 131.8192
                },
                "Scale": {
                  "ScaleX": 1.0,
                  "ScaleY": 1.0
                },
                "CColor": {
                  "R": 106,
                  "G": 0,
                  "B": 95
                },
                "IconVisible": false,
                "PositionPercentXEnabled": true,
                "PrePosition": {
                  "X": 0.5,
                  "Y": 0.5911
                },
                "PreSize": {
                  "X": 0.3068,
                  "Y": 0.1614
                },
                "LeftMargin": 61.0,
                "RightMargin": 61.0,
                "TopMargin": 73.1808,
                "BottomMargin": 113.8192,
                "Tag": 78,
                "ActionTag": 1829009191,
                "Size": {
                  "X": 54.0,
                  "Y": 36.0
                },
                "Name": "goldTxt",
                "ctype": "TextObjectData"
              },
              {
                "FontSize": 36,
                "LabelText": "¥ 6.00",
                "OutlineColor": {
                  "G": 0,
                  "B": 0
                },
                "ShadowColor": {
                  "R": 110,
                  "G": 110,
                  "B": 110
                },
                "ShadowOffsetX": 2.0,
                "ShadowOffsetY": -2.0,
                "AnchorPoint": {
                  "ScaleX": 0.5,
                  "ScaleY": 0.5
                },
                "Position": {
                  "X": 88.0,
                  "Y": 24.2906
                },
                "Scale": {
                  "ScaleX": 1.0,
                  "ScaleY": 1.0
                },
                "CColor": {
                  "R": 106,
                  "G": 0,
                  "B": 95
                },
                "IconVisible": false,
                "PositionPercentXEnabled": true,
                "PrePosition": {
                  "X": 0.5,
                  "Y": 0.1089
                },
                "PreSize": {
                  "X": 0.6136,
                  "Y": 0.1614
                },
                "LeftMargin": 34.0,
                "RightMargin": 34.0,
                "TopMargin": 180.7094,
                "BottomMargin": 6.2906,
                "Tag": 79,
                "ActionTag": -604328502,
                "Size": {
                  "X": 108.0,
                  "Y": 36.0
                },
                "Name": "priceTxt",
                "ctype": "TextObjectData"
              }
            ],
            "ActionTag": -964664995,
            "Size": {
              "X": 176.0,
              "Y": 223.0
            },
            "Name": "item_0",
            "ctype": "ButtonObjectData"
          },
          {
            "FontSize": 14,
            "ButtonText": "",
            "TextColor": {
              "R": 65,
              "G": 65,
              "B": 70
            },
            "DisabledFileData": {
              "Type": "Normal",
              "Path": "shop/itemBg.png",
              "Plist": ""
            },
            "PressedFileData": {
              "Type": "Normal",
              "Path": "shop/itemBg.png",
              "Plist": ""
            },
            "NormalFileData": {
              "Type": "Normal",
              "Path": "shop/itemBg.png",
              "Plist": ""
            },
            "Scale9Enable": true,
            "Scale9OriginX": 15,
            "Scale9OriginY": 11,
            "Scale9Width": 146,
            "Scale9Height": 201,
            "OutlineColor": {
              "G": 0,
              "B": 0
            },
            "ShadowColor": {
              "R": 110,
              "G": 110,
              "B": 110
            },
            "ShadowOffsetX": 2.0,
            "ShadowOffsetY": -2.0,
            "TouchEnable": true,
            "AnchorPoint": {
              "ScaleX": 0.5,
              "ScaleY": 0.5
            },
            "Position": {
              "X": 536.7303,
              "Y": 942.4209
            },
            "Scale": {
              "ScaleX": 1.0,
              "ScaleY": 1.0
            },
            "CColor": {},
            "IconVisible": false,
            "PrePosition": {
              "X": 0.7156,
              "Y": 0.7065
            },
            "PreSize": {
              "X": 0.2347,
              "Y": 0.1672
            },
            "LeftMargin": 448.7303,
            "RightMargin": 125.2697,
            "TopMargin": 280.0791,
            "BottomMargin": 830.9209,
            "Tag": 80,
            "Children": [
              {
                "FontSize": 36,
                "LabelText": "X20",
                "OutlineColor": {
                  "G": 0,
                  "B": 0
                },
                "ShadowColor": {
                  "R": 110,
                  "G": 110,
                  "B": 110
                },
                "ShadowOffsetX": 2.0,
                "ShadowOffsetY": -2.0,
                "AnchorPoint": {
                  "ScaleX": 0.5,
                  "ScaleY": 0.5
                },
                "Position": {
                  "X": 88.0,
                  "Y": 131.8192
                },
                "Scale": {
                  "ScaleX": 1.0,
                  "ScaleY": 1.0
                },
                "CColor": {
                  "R": 106,
                  "G": 0,
                  "B": 95
                },
                "IconVisible": false,
                "PositionPercentXEnabled": true,
                "PrePosition": {
                  "X": 0.5,
                  "Y": 0.5911
                },
                "PreSize": {
                  "X": 0.3068,
                  "Y": 0.1614
                },
                "LeftMargin": 61.0,
                "RightMargin": 61.0,
                "TopMargin": 73.1808,
                "BottomMargin": 113.8192,
                "Tag": 81,
                "ActionTag": -224945642,
                "Size": {
                  "X": 54.0,
                  "Y": 36.0
                },
                "Name": "goldTxt",
                "ctype": "TextObjectData"
              },
              {
                "FontSize": 36,
                "LabelText": "¥ 12.00",
                "OutlineColor": {
                  "G": 0,
                  "B": 0
                },
                "ShadowColor": {
                  "R": 110,
                  "G": 110,
                  "B": 110
                },
                "ShadowOffsetX": 2.0,
                "ShadowOffsetY": -2.0,
                "AnchorPoint": {
                  "ScaleX": 0.5,
                  "ScaleY": 0.5
                },
                "Position": {
                  "X": 88.0,
                  "Y": 24.2906
                },
                "Scale": {
                  "ScaleX": 1.0,
                  "ScaleY": 1.0
                },
                "CColor": {
                  "R": 106,
                  "G": 0,
                  "B": 95
                },
                "IconVisible": false,
                "PositionPercentXEnabled": true,
                "PrePosition": {
                  "X": 0.5,
                  "Y": 0.1089
                },
                "PreSize": {
                  "X": 0.7159,
                  "Y": 0.1614
                },
                "LeftMargin": 25.0,
                "RightMargin": 25.0,
                "TopMargin": 180.7094,
                "BottomMargin": 6.2906,
                "Tag": 82,
                "ActionTag": -551513498,
                "Size": {
                  "X": 126.0,
                  "Y": 36.0
                },
                "Name": "priceTxt",
                "ctype": "TextObjectData"
              }
            ],
            "ActionTag": -1785459840,
            "Size": {
              "X": 176.0,
              "Y": 223.0
            },
            "Name": "item_1",
            "ctype": "ButtonObjectData"
          },
          {
            "FontSize": 14,
            "ButtonText": "",
            "TextColor": {
              "R": 65,
              "G": 65,
              "B": 70
            },
            "DisabledFileData": {
              "Type": "Normal",
              "Path": "shop/itemBg.png",
              "Plist": ""
            },
            "PressedFileData": {
              "Type": "Normal",
              "Path": "shop/itemBg.png",
              "Plist": ""
            },
            "NormalFileData": {
              "Type": "Normal",
              "Path": "shop/itemBg.png",
              "Plist": ""
            },
            "Scale9Enable": true,
            "Scale9OriginX": 15,
            "Scale9OriginY": 11,
            "Scale9Width": 146,
            "Scale9Height": 201,
            "OutlineColor": {
              "G": 0,
              "B": 0
            },
            "ShadowColor": {
              "R": 110,
              "G": 110,
              "B": 110
            },
            "ShadowOffsetX": 2.0,
            "ShadowOffsetY": -2.0,
            "TouchEnable": true,
            "AnchorPoint": {
              "ScaleX": 0.5,
              "ScaleY": 0.5
            },
            "Position": {
              "X": 206.2203,
              "Y": 634.791
            },
            "Scale": {
              "ScaleX": 1.0,
              "ScaleY": 1.0
            },
            "CColor": {},
            "IconVisible": false,
            "PrePosition": {
              "X": 0.275,
              "Y": 0.4759
            },
            "PreSize": {
              "X": 0.2347,
              "Y": 0.1672
            },
            "LeftMargin": 118.2203,
            "RightMargin": 455.7797,
            "TopMargin": 587.709,
            "BottomMargin": 523.291,
            "Tag": 83,
            "Children": [
              {
                "FontSize": 36,
                "LabelText": "X30",
                "OutlineColor": {
                  "G": 0,
                  "B": 0
                },
                "ShadowColor": {
                  "R": 110,
                  "G": 110,
                  "B": 110
                },
                "ShadowOffsetX": 2.0,
                "ShadowOffsetY": -2.0,
                "AnchorPoint": {
                  "ScaleX": 0.5,
                  "ScaleY": 0.5
                },
                "Position": {
                  "X": 88.0,
                  "Y": 131.8192
                },
                "Scale": {
                  "ScaleX": 1.0,
                  "ScaleY": 1.0
                },
                "CColor": {
                  "R": 106,
                  "G": 0,
                  "B": 95
                },
                "IconVisible": false,
                "PositionPercentXEnabled": true,
                "PrePosition": {
                  "X": 0.5,
                  "Y": 0.5911
                },
                "PreSize": {
                  "X": 0.3068,
                  "Y": 0.1614
                },
                "LeftMargin": 61.0,
                "RightMargin": 61.0,
                "TopMargin": 73.1808,
                "BottomMargin": 113.8192,
                "Tag": 84,
                "ActionTag": -2131902836,
                "Size": {
                  "X": 54.0,
                  "Y": 36.0
                },
                "Name": "goldTxt",
                "ctype": "TextObjectData"
              },
              {
                "FontSize": 36,
                "LabelText": "¥ 18.00",
                "OutlineColor": {
                  "G": 0,
                  "B": 0
                },
                "ShadowColor": {
                  "R": 110,
                  "G": 110,
                  "B": 110
                },
                "ShadowOffsetX": 2.0,
                "ShadowOffsetY": -2.0,
                "AnchorPoint": {
                  "ScaleX": 0.5,
                  "ScaleY": 0.5
                },
                "Position": {
                  "X": 88.0,
                  "Y": 24.2906
                },
                "Scale": {
                  "ScaleX": 1.0,
                  "ScaleY": 1.0
                },
                "CColor": {
                  "R": 106,
                  "G": 0,
                  "B": 95
                },
                "IconVisible": false,
                "PositionPercentXEnabled": true,
                "PrePosition": {
                  "X": 0.5,
                  "Y": 0.1089
                },
                "PreSize": {
                  "X": 0.7159,
                  "Y": 0.1614
                },
                "LeftMargin": 25.0,
                "RightMargin": 25.0,
                "TopMargin": 180.7094,
                "BottomMargin": 6.2906,
                "Tag": 85,
                "ActionTag": -1357828441,
                "Size": {
                  "X": 126.0,
                  "Y": 36.0
                },
                "Name": "priceTxt",
                "ctype": "TextObjectData"
              }
            ],
            "ActionTag": -2121103962,
            "Size": {
              "X": 176.0,
              "Y": 223.0
            },
            "Name": "item_2",
            "ctype": "ButtonObjectData"
          },
          {
            "FontSize": 14,
            "ButtonText": "",
            "TextColor": {
              "R": 65,
              "G": 65,
              "B": 70
            },
            "DisabledFileData": {
              "Type": "Normal",
              "Path": "shop/itemBg.png",
              "Plist": ""
            },
            "PressedFileData": {
              "Type": "Normal",
              "Path": "shop/itemBg.png",
              "Plist": ""
            },
            "NormalFileData": {
              "Type": "Normal",
              "Path": "shop/itemBg.png",
              "Plist": ""
            },
            "Scale9Enable": true,
            "Scale9OriginX": 15,
            "Scale9OriginY": 11,
            "Scale9Width": 146,
            "Scale9Height": 201,
            "OutlineColor": {
              "G": 0,
              "B": 0
            },
            "ShadowColor": {
              "R": 110,
              "G": 110,
              "B": 110
            },
            "ShadowOffsetX": 2.0,
            "ShadowOffsetY": -2.0,
            "TouchEnable": true,
            "AnchorPoint": {
              "ScaleX": 0.5,
              "ScaleY": 0.5
            },
            "Position": {
              "X": 536.7302,
              "Y": 634.791
            },
            "Scale": {
              "ScaleX": 1.0,
              "ScaleY": 1.0
            },
            "CColor": {},
            "IconVisible": false,
            "PrePosition": {
              "X": 0.7156,
              "Y": 0.4759
            },
            "PreSize": {
              "X": 0.2347,
              "Y": 0.1672
            },
            "LeftMargin": 448.7302,
            "RightMargin": 125.2698,
            "TopMargin": 587.709,
            "BottomMargin": 523.291,
            "Tag": 86,
            "Children": [
              {
                "FontSize": 36,
                "LabelText": "X60",
                "OutlineColor": {
                  "G": 0,
                  "B": 0
                },
                "ShadowColor": {
                  "R": 110,
                  "G": 110,
                  "B": 110
                },
                "ShadowOffsetX": 2.0,
                "ShadowOffsetY": -2.0,
                "AnchorPoint": {
                  "ScaleX": 0.5,
                  "ScaleY": 0.5
                },
                "Position": {
                  "X": 88.0,
                  "Y": 131.8192
                },
                "Scale": {
                  "ScaleX": 1.0,
                  "ScaleY": 1.0
                },
                "CColor": {
                  "R": 106,
                  "G": 0,
                  "B": 95
                },
                "IconVisible": false,
                "PositionPercentXEnabled": true,
                "PrePosition": {
                  "X": 0.5,
                  "Y": 0.5911
                },
                "PreSize": {
                  "X": 0.3068,
                  "Y": 0.1614
                },
                "LeftMargin": 61.0,
                "RightMargin": 61.0,
                "TopMargin": 73.1808,
                "BottomMargin": 113.8192,
                "Tag": 87,
                "ActionTag": -864144018,
                "Size": {
                  "X": 54.0,
                  "Y": 36.0
                },
                "Name": "goldTxt",
                "ctype": "TextObjectData"
              },
              {
                "FontSize": 36,
                "LabelText": "¥ 30.00",
                "OutlineColor": {
                  "G": 0,
                  "B": 0
                },
                "ShadowColor": {
                  "R": 110,
                  "G": 110,
                  "B": 110
                },
                "ShadowOffsetX": 2.0,
                "ShadowOffsetY": -2.0,
                "AnchorPoint": {
                  "ScaleX": 0.5,
                  "ScaleY": 0.5
                },
                "Position": {
                  "X": 88.0,
                  "Y": 24.2906
                },
                "Scale": {
                  "ScaleX": 1.0,
                  "ScaleY": 1.0
                },
                "CColor": {
                  "R": 106,
                  "G": 0,
                  "B": 95
                },
                "IconVisible": false,
                "PositionPercentXEnabled": true,
                "PrePosition": {
                  "X": 0.5,
                  "Y": 0.1089
                },
                "PreSize": {
                  "X": 0.7159,
                  "Y": 0.1614
                },
                "LeftMargin": 25.0,
                "RightMargin": 25.0,
                "TopMargin": 180.7094,
                "BottomMargin": 6.2906,
                "Tag": 88,
                "ActionTag": 1066829079,
                "Size": {
                  "X": 126.0,
                  "Y": 36.0
                },
                "Name": "priceTxt",
                "ctype": "TextObjectData"
              }
            ],
            "ActionTag": -652068924,
            "Size": {
              "X": 176.0,
              "Y": 223.0
            },
            "Name": "item_3",
            "ctype": "ButtonObjectData"
          }
        ],
        "Size": {
          "X": 750.0,
          "Y": 1334.0
        },
        "Name": "Layer",
        "ctype": "LayerObjectData"
      },
      "UsedResources": [
        "mainBg.png",
        "setting/guanbi.png",
        "shop/itemBg.png"
      ],
      "ctype": "GameFileData"
    }
  },
  "Type": "Layer"
}